keras_vision/__init__.py
keras_vision/MobileViT_v1/__init__.py
keras_vision/MobileViT_v1/base_layers.py
keras_vision/MobileViT_v1/configs.py
keras_vision/MobileViT_v1/mobile_vit_v1.py
keras_vision/MobileViT_v1/mobile_vit_v1_block.py
keras_vision/MobileViT_v1/multihead_self_attention_2D.py
keras_vision/MobileViT_v1/utils.py
keras_vision/MobileViT_v2/__init__.py
keras_vision/MobileViT_v2/base_layers.py
keras_vision/MobileViT_v2/configs.py
keras_vision/MobileViT_v2/linear_attention.py
keras_vision/MobileViT_v2/mobile_vit_v2.py
keras_vision/MobileViT_v2/mobile_vit_v2_block.py
keras_vision/MobileViT_v2/utils.py
keras_vision/fastvit/__init__.py
keras_vision/fastvit/base_layers.py
keras_vision/fastvit/conv_ffn.py
keras_vision/fastvit/fastvit.py
keras_vision/fastvit/mobileone.py
keras_vision/fastvit/multihead_self_attention.py
keras_vision/fastvit/rep_cpe.py
keras_vision/fastvit/replknet.py
keras_vision/fastvit/squeeze_excite.py
keras_vision-0.6.3.dist-info/METADATA
keras_vision-0.6.3.dist-info/WHEEL
keras_vision-0.6.3.dist-info/top_level.txt
keras_vision-0.6.3.dist-info/RECORD
